panda3d_frame/Frame.py
panda3d_frame/__init__.py
panda3d_frame/editorLogHandler.py
panda3d_frame/Extensions/__init__.py
panda3d_frame/Extensions/NodeEditor/NodeEditorExtender.py
panda3d_frame/Extensions/NodeEditor/__init__.py
panda3d_frame/Extensions/NodeEditor/Exporters/PythonExporter.py
panda3d_frame/Extensions/NodeEditor/Exporters/__init__.py
panda3d_frame/Extensions/NodeEditor/Nodes/P3DCallScriptNode.py
panda3d_frame/Extensions/NodeEditor/Nodes/P3DEventNode.py
panda3d_frame/Extensions/NodeEditor/Nodes/P3DScriptLoaderNode.py
panda3d_frame/Extensions/NodeEditor/Nodes/__init__.py
panda3d_frame/Extensions/NodeEditor/Sockets/TextSocket.py
panda3d_frame/Extensions/NodeEditor/Sockets/__init__.py
panda3d_frame/GUI/EditorSelection.py
panda3d_frame/GUI/MainView.py
panda3d_frame/GUI/MenuBar.py
panda3d_frame/GUI/__init__.py
panda3d_frame/GUI/InternalEditors/EditorStore.py
panda3d_frame/GUI/InternalEditors/__init__.py
panda3d_frame/GUI/ProjectManagement/NewProjectDialog.py
panda3d_frame/GUI/ProjectManagement/NewProjectDialogHandler.py
panda3d_frame/GUI/ProjectManagement/__init__.py
panda3d_frame/GUI/Terminal/Terminal.py
panda3d_frame/GUI/Terminal/TerminalWindow.py
panda3d_frame/GUI/Terminal/__init__.py
panda3d_frame/core/FrameProject.py
panda3d_frame/core/PmanProject.py
panda3d_frame/core/ProjectManager.py
panda3d_frame/core/__init__.py
panda3d_frame/editors/DirectGuiDesigner.json
panda3d_frame/editors/EditorSelectionGD.png
panda3d_frame/editors/EditorSelectionNE.png
panda3d_frame/editors/EditorSelectionSE.png
panda3d_frame/editors/NodeEditor.json
panda3d_frame/editors/SceneEditor.json
panda3d_frame/icons/EditorSelectionStore.png
panda3d_frame/templates/requirements.txt
panda3d_frame/templates/setup.cfg
panda3d_frame/templates/setup.py
panda3d_frame/templates/Editor/EditorBase.py
panda3d_frame/templates/Editor/editorDefinition.json
panda3d_frame/templates/baseProject/config.py
panda3d_frame/templates/baseProject/coreFSM.py
panda3d_frame/templates/baseProject/main.py
panda3d_frame-22.10.post1.dist-info/LICENSE
panda3d_frame-22.10.post1.dist-info/METADATA
panda3d_frame-22.10.post1.dist-info/WHEEL
panda3d_frame-22.10.post1.dist-info/entry_points.txt
panda3d_frame-22.10.post1.dist-info/top_level.txt
panda3d_frame-22.10.post1.dist-info/RECORD
