Metadata-Version: 2.1
Name: panda3d-frame
Version: 22.10.post1
Summary: A visual game editor for the Panda3D engine
Home-page: https://github.com/fireclawthefox/frame
Author: Fireclaw
Author-email: fireclawthefox@gmail.com
Classifier: Programming Language :: Python :: 3
Classifier: License :: OSI Approved :: BSD License
Classifier: Operating System :: OS Independent
Classifier: Development Status :: 3 - Alpha
Classifier: Intended Audience :: Developers
Classifier: Intended Audience :: End Users/Desktop
Classifier: Topic :: Software Development :: User Interfaces
Requires-Python: >=3.6
License-File: LICENSE
Requires-Dist: panda3d (~=1.10.11)
Requires-Dist: DirectFolderBrowser
Requires-Dist: DirectGuiExtension (~=22.09)
